LICENSE
MANIFEST.in
README.md
requirements.txt
setup.py
cloudfoundry/__init__.py
cloudfoundry/apps.py
cloudfoundry/services.py
python_cloudfoundry.egg-info/PKG-INFO
python_cloudfoundry.egg-info/SOURCES.txt
python_cloudfoundry.egg-info/dependency_links.txt
python_cloudfoundry.egg-info/requires.txt
python_cloudfoundry.egg-info/top_level.txt