Metadata-Version: 1.0
Name: python-cloudfoundry
Version: 0.3
Summary: Python interface to CloudFoundry
Home-page: http://www.github.com/KristianOellegaard/python-cloudfoundry/
Author: Kristian Øllegaard
Author-email: kristian@oellegaard.com
License: MIT License
Platform: UNKNOWN
Classifier: Development Status :: 3 - Alpha
Classifier: Intended Audience :: Developers
Classifier: Operating System :: OS Independent
Classifier: Programming Language :: Python
Classifier: Topic :: Software Development :: Libraries
Classifier: Topic :: Software Development :: Libraries :: Python Modules
